LICENSE.txt
MANIFEST.in
README.rst
setup.cfg
setup.py
xonotic_exporter/__init__.py
xonotic_exporter/cli.py
xonotic_exporter/config_schema.json
xonotic_exporter/metrics_parser.py
xonotic_exporter/server.py
xonotic_exporter/xonotic.py
xonotic_exporter.egg-info/PKG-INFO
xonotic_exporter.egg-info/SOURCES.txt
xonotic_exporter.egg-info/dependency_links.txt
xonotic_exporter.egg-info/entry_points.txt
xonotic_exporter.egg-info/requires.txt
xonotic_exporter.egg-info/top_level.txt
xonotic_exporter/templates/index.mako
xonotic_exporter/templates/metrics.mako