Metadata-Version: 1.1
Name: xonotic-exporter
Version: 0.1
Summary: Xonotic metrics exporter for prometheus monitoring
Home-page: UNKNOWN
Author: Slava Bacherikov
Author-email: slava@bacher09.org
License: GPLv3
Keywords: rcon,xonotic,darkplaces,quake,nexuiz,prometheusnexuiz,metrics,monitoring
Platform: any
Classifier: Development Status :: 3 - Alpha
Classifier: Operating System :: OS Independent
Classifier: Programming Language :: Python
Classifier: Programming Language :: Python :: 3.5
Classifier: Programming Language :: Python :: 3.6
Classifier: Programming Language :: Python :: 3 :: Only
Classifier: Topic :: Internet
Classifier: Topic :: Games/Entertainment
Classifier: Topic :: Games/Entertainment :: First Person Shooters
Classifier: License :: OSI Approved :: GNU General Public License v3 (GPLv3)
